cusir/__init__.py
cusir/system.py
cusir-1.0.0.dist-info/LICENSE
cusir-1.0.0.dist-info/METADATA
cusir-1.0.0.dist-info/WHEEL
cusir-1.0.0.dist-info/top_level.txt
cusir-1.0.0.dist-info/RECORD
