Metadata-Version: 2.1
Name: cusir
Version: 1.0.0
Summary: A SIR diffusive model based in CuPy solver
Author-email: renzozs <renzozagarrasaez@gmail.com>
Project-URL: Homepage, https://github.com/RenzoZS/CuSIR
Project-URL: Bug Tracker, https://github.com/RenzoZS/CuSIR/issues
Keywords: sir,epidemiology,CuPy,GPU,CUDA,diffusion,reaction-diffusion,parallel computing
Classifier: Programming Language :: Python :: 3
Classifier: License :: OSI Approved :: MIT License
Classifier: Operating System :: OS Independent
Requires-Python: >=3.7
License-File: LICENSE
